scrapy_proxy_pool/__init__.py
scrapy_proxy_pool/middlewares.py
scrapy_proxy_pool/policy.py
sriram_proxy_pool-0.2.2.dist-info/METADATA
sriram_proxy_pool-0.2.2.dist-info/WHEEL
sriram_proxy_pool-0.2.2.dist-info/top_level.txt
sriram_proxy_pool-0.2.2.dist-info/RECORD
