Metadata-Version: 2.1
Name: sriram-proxy-pool
Version: 0.2.2
Summary: SDT scrapy proxy pool
Home-page: https://github.com/sriramkumar1996/scrapy-proxy-pool
Author: Sriram Kumar
Author-email: srirambsk1996@gmail.com
License: MIT
Platform: UNKNOWN
Classifier: Development Status :: 3 - Alpha
Classifier: License :: OSI Approved :: MIT License
Classifier: Intended Audience :: Developers
Classifier: Operating System :: OS Independent
Classifier: Framework :: Scrapy
Classifier: Programming Language :: Python
Classifier: Programming Language :: Python :: 2
Classifier: Programming Language :: Python :: 2.7
Classifier: Programming Language :: Python :: 3
Classifier: Programming Language :: Python :: 3.4
Classifier: Programming Language :: Python :: 3.5
Classifier: Programming Language :: Python :: 3.6
Requires-Dist: scrapy
Requires-Dist: sriram-proxyscrape
